streamlit_searchbox/__init__.py
streamlit_searchbox/frontend/build/asset-manifest.json
streamlit_searchbox/frontend/build/bootstrap.min.css
streamlit_searchbox/frontend/build/index.html
streamlit_searchbox/frontend/build/static/js/main.99d28be7.js
streamlit_searchbox/frontend/build/static/js/main.99d28be7.js.LICENSE.txt
streamlit_searchbox/frontend/build/static/js/main.99d28be7.js.map
streamlit_searchbox-0.1.22.dist-info/LICENSE
streamlit_searchbox-0.1.22.dist-info/METADATA
streamlit_searchbox-0.1.22.dist-info/WHEEL
streamlit_searchbox-0.1.22.dist-info/top_level.txt
streamlit_searchbox-0.1.22.dist-info/RECORD
